pytest_custom_outputs/__init__.py
pytest_custom_outputs/custom_outputs.py
pytest_custom_outputs-1.1.1.dist-info/LICENSE
pytest_custom_outputs-1.1.1.dist-info/METADATA
pytest_custom_outputs-1.1.1.dist-info/WHEEL
pytest_custom_outputs-1.1.1.dist-info/entry_points.txt
pytest_custom_outputs-1.1.1.dist-info/top_level.txt
pytest_custom_outputs-1.1.1.dist-info/RECORD
